MANIFEST.in
README.md
setup.py
polaris/__init__.py
polaris/cmd.py
polaris/convert.py
polaris/defaults.py
polaris/exc.py
polaris/models.py
polaris/patch.py
polaris/server.py
polaris/utils.py
polaris/wsgi.py
polaris.egg-info/PKG-INFO
polaris.egg-info/SOURCES.txt
polaris.egg-info/dependency_links.txt
polaris.egg-info/entry_points.txt
polaris.egg-info/not-zip-safe
polaris.egg-info/requires.txt
polaris.egg-info/top_level.txt
polaris/auth/__init__.py
polaris/auth/form.py
polaris/auth/login.py
polaris/auth/oauth.py
polaris/auth/principal.py
polaris/auth/signup.py
polaris/ext/__init__.py
polaris/ext/database.py
polaris/ext/rand.py
polaris/static/css/polaris.css
polaris/static/flatui/.git
polaris/static/flatui/.gitignore
polaris/static/flatui/README.md
polaris/static/flatui/components.html
polaris/static/flatui/getting-started.html
polaris/static/flatui/index.html
polaris/static/flatui/package.json
polaris/static/flatui/template.html
polaris/static/flatui/bootstrap/css/bootstrap-docs.css
polaris/static/flatui/bootstrap/css/bootstrap.css
polaris/static/flatui/bootstrap/css/prettify.css
polaris/static/flatui/bootstrap/fonts/glyphicons-halflings-regular.eot
polaris/static/flatui/bootstrap/fonts/glyphicons-halflings-regular.svg
polaris/static/flatui/bootstrap/fonts/glyphicons-halflings-regular.ttf
polaris/static/flatui/bootstrap/fonts/glyphicons-halflings-regular.woff
polaris/static/flatui/bootstrap/js/application.js
polaris/static/flatui/bootstrap/js/holder.js
polaris/static/flatui/bootstrap/js/google-code-prettify/prettify.js
polaris/static/flatui/css/demo.css
polaris/static/flatui/css/docs.css
polaris/static/flatui/css/flat-ui.css
polaris/static/flatui/fonts/Flat-UI-Icons.dev.svg
polaris/static/flatui/fonts/Flat-UI-Icons.eot
polaris/static/flatui/fonts/Flat-UI-Icons.svg
polaris/static/flatui/fonts/Flat-UI-Icons.ttf
polaris/static/flatui/fonts/Flat-UI-Icons.woff
polaris/static/flatui/fonts/icomoon-session.json
polaris/static/flatui/fonts/lato/lato-black-webfont.eot
polaris/static/flatui/fonts/lato/lato-black-webfont.svg
polaris/static/flatui/fonts/lato/lato-black-webfont.ttf
polaris/static/flatui/fonts/lato/lato-black-webfont.woff
polaris/static/flatui/fonts/lato/lato-bold-webfont.eot
