Metadata-Version: 1.0
Name: polaris
Version: 0.1
Summary: Dashboard made easy.
Home-page: UNKNOWN
Author: Lx Yu
Author-email: i@lxyu.net
License: MIT
Keywords: data virtualization analysis dashboard
Platform: UNKNOWN
